wf_fastapi_auth0/__init__.py
wf_fastapi_auth0/wf_permissions/__init__.py
wf_fastapi_auth0-1.0.5.dist-info/WHEEL
wf_fastapi_auth0-1.0.5.dist-info/METADATA
wf_fastapi_auth0-1.0.5.dist-info/RECORD
