Metadata-Version: 2.1
Name: wf-fastapi-auth0
Version: 1.0.5
Summary: Library to simplify adding Auth0 support to FastAPI
Home-page: https://github.com/WildflowerSchools/wf-fastapi-auth0
Author: Paul DeCoursey
Author-email: paul.decoursey@wildflowerschools.org
Maintainer: Benjamin Jaffe-Talberg
Maintainer-email: ben.talberg@wildflowerschools.org
Requires-Python: >=3.8,<4.0
Classifier: Intended Audience :: Developers
Classifier: License :: OSI Approved :: MIT License
Classifier: Operating System :: POSIX :: Linux
Classifier: Programming Language :: Python
Classifier: Programming Language :: Python :: 3
Classifier: Programming Language :: Python :: 3.8
Classifier: Programming Language :: Python :: 3.9
Classifier: Programming Language :: Python :: 3.10
Classifier: Programming Language :: Python :: 3.11
Requires-Dist: auth0-python (>=3.24.0,<4.0.0)
Requires-Dist: cachetools (>=5.2.1,<6.0.0)
Requires-Dist: fastapi (>=0.89.1)
Requires-Dist: python-jose (>=3.3.0,<4.0.0)
Requires-Dist: requests (>=2.28.2,<3.0.0)
Project-URL: Repository, https://github.com/WildflowerSchools/wf-fastapi-auth0
